{
"label": "14 2011-04-30"  , "room": "FC31"  , "path": "meters.cl.cam.ac.uk/elec/primary-cs2-riser/F-sockets"  , "description": "Sockets"  , "coverage": "First Central"  , "type": "Auto Meter IC970"  , "ts": "2011-04-30"  ,
"data": { "start" : 1304204520000 , "step" : 120000, "readings": [
0.090, 0.111, 0.100, 0.110, 0.099, 0.110, 0.101, 0.090, 0.100, 0.109, 
0.090, 0.090, 0.091, 0.090, 0.089, 0.120, 0.091, 0.100, 0.099, 0.090, 
0.090, 0.091, 0.100, 0.110, 0.099, 0.091, 0.090, 0.089, 0.090]}
}
